laconia/__init__.py
laconia/_version.py
laconia-0.6.0.dist-info/LICENCE
laconia-0.6.0.dist-info/METADATA
laconia-0.6.0.dist-info/WHEEL
laconia-0.6.0.dist-info/top_level.txt
laconia-0.6.0.dist-info/RECORD
