Metadata-Version: 2.1
Name: laconia
Version: 0.6.0
Summary: Simple API for RDF
Home-page: http://github.com/avengerpenguin/laconia
Author: Ross Fenning
Author-email: ross.fenning@gmail.com
License: GPLv3+
Platform: UNKNOWN
Classifier: License :: OSI Approved :: GNU General Public License v3 or later (GPLv3+)
Classifier: Operating System :: OS Independent
Classifier: Programming Language :: Python
Classifier: Topic :: Software Development :: Libraries :: Python Modules
License-File: LICENCE
Requires-Dist: rdflib
Provides-Extra: test
Requires-Dist: pytest ; extra == 'test'
Requires-Dist: pytest-pikachu ; extra == 'test'
Requires-Dist: pytest-mypy ; extra == 'test'
